{
	"_version": "1.1.0",
	"resources": [
		{
			"name": ".theming",
			"size": 137,
			"theme": "sap_bluecrystal"
		},
		{
			"name": "DynamicPage.less",
			"size": 427,
			"designtime": true,
			"theme": "sap_bluecrystal"
		},
		{
			"name": "DynamicPageHeader.less",
			"size": 264,
			"designtime": true,
			"theme": "sap_bluecrystal"
		},
		{
			"name": "DynamicPageTitle.less",
			"size": 259,
			"designtime": true,
			"theme": "sap_bluecrystal"
		},
		{
			"name": "FlexibleColumnLayout.less",
			"size": 992,
			"designtime": true,
			"theme": "sap_bluecrystal"
		},
		{
			"name": "css-variables.css",
			"size": 3153,
			"theme": "sap_bluecrystal"
		},
		{
			"name": "css-variables.source.less",
			"size": 95757,
			"designtime": true,
			"theme": "sap_bluecrystal"
		},
		{
			"name": "library-RTL.css",
			"size": 59295,
			"theme": "sap_bluecrystal"
		},
		{
			"name": "library-parameters.json",
			"size": 1220,
			"theme": "sap_bluecrystal"
		},
		{
			"name": "library-skeleton-RTL.css",
			"size": 60692,
			"theme": "sap_bluecrystal"
		},
		{
			"name": "library-skeleton.css",
			"size": 60693,
			"theme": "sap_bluecrystal"
		},
		{
			"name": "library.css",
			"size": 59298,
			"theme": "sap_bluecrystal"
		},
		{
			"name": "library.less",
			"size": 2747,
			"designtime": true,
			"theme": "sap_bluecrystal"
		},
		{
			"name": "library.source.less",
			"size": 461,
			"designtime": true,
			"theme": "sap_bluecrystal"
		}
	]
}